RunDeck/API.py
RunDeck/__init__.py
RunDeckAPI-0.0.1.dist-info/METADATA
RunDeckAPI-0.0.1.dist-info/WHEEL
RunDeckAPI-0.0.1.dist-info/top_level.txt
RunDeckAPI-0.0.1.dist-info/RECORD
